MANIFEST.in
setup.py
gmapsbounds/__init__.py
gmapsbounds/constants.py
gmapsbounds/llpx.py
gmapsbounds/obj.py
gmapsbounds/reader.py
gmapsbounds/utils.py
gmapsbounds.egg-info/PKG-INFO
gmapsbounds.egg-info/SOURCES.txt
gmapsbounds.egg-info/dependency_links.txt
gmapsbounds.egg-info/requires.txt
gmapsbounds.egg-info/top_level.txt
scripts/gmapsbounds