Metadata-Version: 1.1
Name: gmapsbounds
Version: 0.1.0
Summary: Extract Lat/Lng boundary points of geographical regions from Google Maps
Home-page: https://github.com/evfredericksen/gmapsbounds
Author: Evan Fredericksen
Author-email: evfredericksen@gmail.com
License: MIT
Keywords: google maps lat lng boundaries
Platform: UNKNOWN
Classifier: Development Status :: 3 - Alpha
Classifier: Intended Audience :: Developers
Classifier: Topic :: Software Development :: Build Tools
Classifier: License :: OSI Approved :: MIT License
Classifier: Programming Language :: Python :: 2
Classifier: Programming Language :: Python :: 2.6
Classifier: Programming Language :: Python :: 2.7
Classifier: Programming Language :: Python :: 3
Classifier: Programming Language :: Python :: 3.2
Classifier: Programming Language :: Python :: 3.3
Classifier: Programming Language :: Python :: 3.4
